zhizhen/__init__.py
zhizhen/test.py
zhizhen-1.0.4.dist-info/METADATA
zhizhen-1.0.4.dist-info/WHEEL
zhizhen-1.0.4.dist-info/top_level.txt
zhizhen-1.0.4.dist-info/RECORD
