Metadata-Version: 2.1
Name: zhizhen
Version: 1.0.4
Summary: zhizhenOs software development library
Home-page: UNKNOWN
Author: Yuanxun Technology
Author-email: yuanxunkj@qq.com
License: UNKNOWN
Platform: UNKNOWN
